makeastar-1.0.dist-info/licenses/LICENSE
star/__init__.py
별/__init__.py
makeastar-1.0.dist-info/METADATA
makeastar-1.0.dist-info/WHEEL
makeastar-1.0.dist-info/top_level.txt
makeastar-1.0.dist-info/RECORD
