Metadata-Version: 2.4
Name: makeastar
Version: 1.0
Summary: Minimalist star pattern generator using optimized one-liners.
Author-email: "Rheehose (Rhee Creative)" <rheehose@rheehose.com>
Project-URL: Homepage, https://github.com/hslcrb/makeastar
Classifier: Programming Language :: Python :: 3
Classifier: Operating System :: OS Independent
Requires-Python: >=3.8
License-File: LICENSE
Dynamic: license-file
